odoo/addons/stock_landed_cost_company_percentage/README.rst
odoo/addons/stock_landed_cost_company_percentage/__init__.py
odoo/addons/stock_landed_cost_company_percentage/__manifest__.py
odoo/addons/stock_landed_cost_company_percentage/i18n/stock_landed_cost_company_percentage.pot
odoo/addons/stock_landed_cost_company_percentage/models/__init__.py
odoo/addons/stock_landed_cost_company_percentage/models/landed_cost_company_line.py
odoo/addons/stock_landed_cost_company_percentage/models/res_company.py
odoo/addons/stock_landed_cost_company_percentage/models/stock_picking.py
odoo/addons/stock_landed_cost_company_percentage/security/ir.model.access.csv
odoo/addons/stock_landed_cost_company_percentage/static/description/icon.png
odoo/addons/stock_landed_cost_company_percentage/tests/__init__.py
odoo/addons/stock_landed_cost_company_percentage/tests/test_stock_orderpoint_manual_procurement.py
odoo/addons/stock_landed_cost_company_percentage/views/res_company_view.xml
odoo11_addon_stock_landed_cost_company_percentage-11.0.1.0.0.99.dev3.dist-info/DESCRIPTION.rst
odoo11_addon_stock_landed_cost_company_percentage-11.0.1.0.0.99.dev3.dist-info/METADATA
odoo11_addon_stock_landed_cost_company_percentage-11.0.1.0.0.99.dev3.dist-info/RECORD
odoo11_addon_stock_landed_cost_company_percentage-11.0.1.0.0.99.dev3.dist-info/WHEEL
odoo11_addon_stock_landed_cost_company_percentage-11.0.1.0.0.99.dev3.dist-info/metadata.json
odoo11_addon_stock_landed_cost_company_percentage-11.0.1.0.0.99.dev3.dist-info/top_level.txt
